CHANGES.txt
LICENSE.txt
MANIFEST.in
README.txt
setup.py
js/__init__.py
js.augment.egg-info/PKG-INFO
js.augment.egg-info/SOURCES.txt
js.augment.egg-info/dependency_links.txt
js.augment.egg-info/entry_points.txt
js.augment.egg-info/namespace_packages.txt
js.augment.egg-info/not-zip-safe
js.augment.egg-info/requires.txt
js.augment.egg-info/top_level.txt
js/augment/__init__.py
js/augment/test_augment.js.txt
js/augment/resources/README.txt
js/augment/resources/augment.js
js/augment/resources/augment.min.js