Metadata-Version: 1.0
Name: js.augment
Version: 0.4.2
Summary: Fanstatic packaging of Augment.js
Home-page: UNKNOWN
Author: Fanstatic Developers
Author-email: fanstatic@googlegroups.com
License: BSD
Platform: UNKNOWN
